portrait_analyser/__init__.py
portrait_analyser/const.py
portrait_analyser/exceptions.py
portrait_analyser/face.py
portrait_analyser/ios.py
portrait_analyser-0.1.2.dist-info/LICENSE
portrait_analyser-0.1.2.dist-info/METADATA
portrait_analyser-0.1.2.dist-info/WHEEL
portrait_analyser-0.1.2.dist-info/RECORD
